<?xml version="1.0" encoding="UTF-8" standalone="no"?>
<transcription xmlns:xsi="http://www.w3.org/2001/XMLSchema-instance" xsi:noNamespaceSchemaLocation="http://www.livesandletters.ac.uk/schema/aor2_18112016.xsd">
    
    <page filename="PrincetonRB16th99a.075v.tif" pagination="[75v]" reader="Harvey"/>
    <annotation>
        
        <underline language="EN" method="pen" text="seede Cake" type="straight"/>
        <underline language="EN" method="pen" text="the Pasties, and furmentie" type="straight"/>
        <underline language="EN" method="pen" text="roast meat on Sundaies, &amp;" type="straight"/>
        <underline language="EN" method="pen" text="Physicke" type="straight"/>
        <underline language="EN" method="pen" text="huswiues prouides, ere an sicknes doo" type="straight"/>
        <underline language="EN" method="pen" text="Aqua composita" type="straight"/>
        <underline language="EN" method="pen" text="Vineger" type="straight"/>
        <underline language="EN" method="pen" text="Rose water " type="straight"/>
        <underline language="EN" method="pen" text="treakle" type="straight"/>
        <underline language="EN" method="pen" text="Cold herbes" type="straight"/>
        <underline language="EN" method="pen" text="White Endiue" type="straight"/>
        <underline language="EN" method="pen" text="Suckerie" type="straight"/>
        <underline language="EN" method="pen" text="Spinnage ynough" type="straight"/>
        <underline language="EN" method="pen" text="good pot herbes" type="straight"/>
        <underline language="EN" method="pen" text="Fumentorie, Liuer to" type="straight"/>
        <underline language="EN" method="pen" text="else lie like a foole" type="straight"/>
        <underline language="EN" method="pen" text="Conserue of the" type="straight"/>
        <underline language="EN" method="pen" text="Quinces" type="straight"/>
        <underline language="EN" method="pen" text="Sirops that" type="straight"/>
        <underline language="EN" method="pen" text="thousands hate physick, because of the" type="straight"/>
        <underline language="EN" method="pen" text="thousands it helpeth, that else should be" type="straight"/>
        <underline language="EN" method="pen" text="Good broth" type="straight"/>
        <underline language="EN" method="pen" text="good keeping, doo" type="straight"/>
        <underline language="EN" method="pen" text="diet with wisedome, best comforteth man" type="straight"/>
        <underline language="EN" method="pen" text="health to be stirring" type="straight"/>
        <underline language="EN" method="pen" text="sicknes hate trouble, séeke" type="straight"/>
        
        <symbol name="SS" place="left_margin"/>
        
        <symbol language="EN" name="SS" place="right_margin" text="diet with wisedome, best comforteth man"/>
        
        <mark language="EN" method="pen" name="plus_sign" place="left_margin" text="yet thousands it helpeth, that else should be lost."/>
        <mark language="EN" method="pen" name="plus_sign" place="left_margin" text="diet with wisedome, best comforteth man"/>
        <mark method="pen" name="bracket" place="left_margin"/>
        <mark language="EN" method="pen" name="plus_sign" place="left_margin" text="sicknes hate trouble, séeke"/>
        
        <mark language="EN" method="pen" name="bracket" place="right_margin" text="Aske Medicus counsell, ere, ere medcine ye make, and honour that man, for necessities sake."/>
        <mark method="pen" name="plus_sign" place="right_margin"/>
        
        <mark language="EN" method="pen" name="plus_sign" place="intext" text="Physicke"/>
        <mark language="EN" method="pen" name="plus_sign" place="intext" text="Physicke"/>
        <mark method="pen" name="dot" place="intext"/> <!-- best, In -->
        
        <drawing anchor_text="thousands hate physick, because of the" book_orientation="0" method="pen" place="right_margin" type="manicule"/>
        
    </annotation>
</transcription>
